IIFLapis/IIFLapis.py
IIFLapis/__init__.py
IIFLapis/auth.py
IIFLapis/conf.py
IIFLapis/const.py
IIFLapis/logging.py
IIFLapis/order.py
IIFLapis-2.1.1.dist-info/AUTHORS.rst
IIFLapis-2.1.1.dist-info/METADATA
IIFLapis-2.1.1.dist-info/WHEEL
IIFLapis-2.1.1.dist-info/top_level.txt
IIFLapis-2.1.1.dist-info/RECORD
