Metadata-Version: 2.1
Name: IIFLapis
Version: 2.1.1
Summary: Python SDK for IIFL Trading APIs
Home-page: UNKNOWN
Author: IIFL Securities
Author-email: apisupport.broking@iifl.com
License: UNKNOWN
Keywords: IIFLapis
Platform: UNKNOWN
Classifier: Development Status :: 2 - Pre-Alpha
Classifier: Intended Audience :: Developers
Classifier: Natural Language :: English
Classifier: Programming Language :: Python :: 3.6
Requires-Python: >=3.6
Requires-Dist: requests
Requires-Dist: pycryptodome (>=3.9.8)
Requires-Dist: certifi (>=2020.4.5.1)
Requires-Dist: chardet (>=3.0.4)
Requires-Dist: pbkdf2 (>=1.3)
Requires-Dist: urllib3 (>=1.25.8)
Requires-Dist: idna (>=2.9)
Requires-Dist: loguru (>=0.5.1)
Requires-Dist: pandas (>=1.2.4)
Requires-Dist: numpy (>=1.20.3)
